README.md
setup.py
tubetone/__init__.py
tubetone/__main__.py
tubetone/constants.py
tubetone/models.py
tubetone.egg-info/PKG-INFO
tubetone.egg-info/SOURCES.txt
tubetone.egg-info/dependency_links.txt
tubetone.egg-info/entry_points.txt
tubetone.egg-info/requires.txt
tubetone.egg-info/top_level.txt
tubetone/analysis/__init__.py
tubetone/analysis/_morph.py
tubetone/analysis/_tone.py
tubetone/db/__init__.py
tubetone/db/_from_db.py
tubetone/db/_into_db.py
tubetone/loader/__init__.py
tubetone/loader/_load.py
tubetone/utils/__init__.py
tubetone/utils/comparator.py
tubetone/utils/operations.py
tubetone/utils/youtube.py