Metadata-Version: 2.1
Name: tubetone
Version: 0.3.2
Summary: Library to process youtube videos texts and analyze results.
Home-page: https://github.com/solovieff/text-anal
Author: Andrey Solovieff
Author-email: solovieff.nnov@gmail.com
License: MIT
Download-URL: https://github.com/solovieff/text-anal/archive/refs/tags/0.3.2.tar.gz
Platform: UNKNOWN
Classifier: Intended Audience :: Developers
Classifier: Development Status :: 4 - Beta
Classifier: License :: OSI Approved :: MIT License
Classifier: Programming Language :: Python
Classifier: Programming Language :: Python :: 3.6
Classifier: Programming Language :: Python :: 3.7
Classifier: Programming Language :: Python :: 3.8
Classifier: Programming Language :: Python :: 3.9
Classifier: Operating System :: OS Independent
